elommr/__init__.py
elommr/elommr.py
elommr-1.2.0.dist-info/LICENSE
elommr-1.2.0.dist-info/METADATA
elommr-1.2.0.dist-info/WHEEL
elommr-1.2.0.dist-info/top_level.txt
elommr-1.2.0.dist-info/RECORD
