Metadata-Version: 2.1
Name: elommr
Version: 1.2.0
Summary: A minimal, Python implementation of the Elo-MMR rating system.
Author: duhby
License: MIT License
Project-URL: Source, https://github.com/duhby/elommr/
Project-URL: Changelog, https://github.com/duhby/elommr/blob/master/CHANGELOG.md
Project-URL: Bug Tracker, https://github.com/duhby/elommr/issues/
Classifier: Development Status :: 5 - Production/Stable
Classifier: Natural Language :: English
Classifier: Programming Language :: Python :: 3.10
Classifier: Programming Language :: Python :: 3.11
Classifier: License :: OSI Approved :: MIT License
Requires-Python: >=3.10
License-File: LICENSE
